mirobo/__init__.py
mirobo/airpurifier.py
mirobo/ceil.py
mirobo/ceil_cli.py
mirobo/chuangmi_ir.py
mirobo/cli.py
mirobo/containers.py
mirobo/device.py
mirobo/discovery.py
mirobo/fan.py
mirobo/philips_eyecare.py
mirobo/philips_eyecare_cli.py
mirobo/plug.py
mirobo/plug_cli.py
mirobo/plug_v1.py
mirobo/protocol.py
mirobo/strip.py
mirobo/vacuum.py
mirobo/vacuum_cli.py
mirobo/vacuumcontainers.py
mirobo/version.py
mirobo/yeelight.py
python_mirobo-0.2.0.dist-info/DESCRIPTION.rst
python_mirobo-0.2.0.dist-info/METADATA
python_mirobo-0.2.0.dist-info/RECORD
python_mirobo-0.2.0.dist-info/WHEEL
python_mirobo-0.2.0.dist-info/entry_points.txt
python_mirobo-0.2.0.dist-info/metadata.json
python_mirobo-0.2.0.dist-info/top_level.txt
