Metadata-Version: 2.0
Name: python-mirobo
Version: 0.2.0
Summary: Python library for interfacing with Xiaomi Vacuum cleaner robot
Home-page: https://github.com/rytilahti/python-mirobo
Author: Teemu Rytilahti
Author-email: tpr@iki.fi
License: GPLv3
Keywords: xiaomi vacuum
Platform: UNKNOWN
Classifier: Development Status :: 3 - Alpha
Classifier: Intended Audience :: Developers
Classifier: License :: OSI Approved :: GNU General Public License v3 (GPLv3)
Classifier: Programming Language :: Python :: 3
Requires-Dist: click
Requires-Dist: construct
Requires-Dist: cryptography
Requires-Dist: pretty-cron
Requires-Dist: typing
Requires-Dist: zeroconf
